win32_sysgrow/__init__.py
win32_sysgrow/choco.py
win32_sysgrow/explorercfg.py
win32_sysgrow/git-bash_vs2022.cmd
win32_sysgrow/main.py
win32_sysgrow/mega.py
win32_sysgrow/nvidia.py
win32_sysgrow/powercfg.py
win32_sysgrow/pythonlinks.py
win32_sysgrow/sysenv.py
win32_sysgrow/vsinstall.py
win32_sysgrow/vswhere.exe
win32_sysgrow/windowsterminal.py
win32_sysgrow/winget.py
win32_sysgrow-1.0.1.dist-info/LICENSE
win32_sysgrow-1.0.1.dist-info/METADATA
win32_sysgrow-1.0.1.dist-info/WHEEL
win32_sysgrow-1.0.1.dist-info/entry_points.txt
win32_sysgrow-1.0.1.dist-info/top_level.txt
win32_sysgrow-1.0.1.dist-info/RECORD
