Metadata-Version: 2.1
Name: win32-sysgrow
Version: 1.0.1
Summary: Python toolkit for automating the installation and configuration of various useful software and system settings on Windows
Author: AleirJDawn
Author-email: 
Classifier: Programming Language :: Python :: 3
Classifier: License :: OSI Approved :: MIT License
Requires-Python: >=3.6
License-File: LICENSE
Requires-Dist: requests
Requires-Dist: tqdm
Requires-Dist: rarfile
Requires-Dist: pywin32
Requires-Dist: pycryptodome
